aptapy/__init__.py
aptapy/_version.py
aptapy/hist.py
aptapy/modeling.py
aptapy/models.py
aptapy/plotting.py
aptapy/py.typed
aptapy/strip.py
aptapy/typing_.py
aptapy/fonts/Humor-Sans.ttf
aptapy/styles/aptapy-dark.mplstyle
aptapy/styles/aptapy-xkcd.mplstyle
aptapy/styles/aptapy.mplstyle
aptapy-0.19.1.dist-info/METADATA
aptapy-0.19.1.dist-info/WHEEL
aptapy-0.19.1.dist-info/licenses/LICENSE
aptapy-0.19.1.dist-info/RECORD
