Metadata-Version: 2.4
Name: aptapy
Version: 0.19.1
Summary: Statistical tools for online monitoring and analysis
Project-URL: Homepage, https://github.com/lucabaldini/aptapy
Project-URL: Issues, https://github.com/lucabaldini/aptapy/issues
Author-email: Luca Baldini <luca.baldini@unipi.it>
License:                     GNU GENERAL PUBLIC LICENSE
License-File: LICENSE
Classifier: Development Status :: 4 - Beta
Classifier: Intended Audience :: Science/Research
Classifier: License :: OSI Approved :: GNU Lesser General Public License v3 or later (LGPLv3+)
Classifier: Operating System :: OS Independent
Classifier: Programming Language :: Python
Classifier: Programming Language :: Python :: 3.7
Classifier: Programming Language :: Python :: 3.13
Classifier: Topic :: Scientific/Engineering
Requires-Python: >=3.7
Requires-Dist: matplotlib
Requires-Dist: numpy
Requires-Dist: scipy
Requires-Dist: uncertainties
Provides-Extra: dev
Requires-Dist: nox; extra == 'dev'
Requires-Dist: packaging; extra == 'dev'
Requires-Dist: pylint; extra == 'dev'
Requires-Dist: pytest; extra == 'dev'
Requires-Dist: ruff; extra == 'dev'
Provides-Extra: docs
Requires-Dist: sphinx; extra == 'docs'
Requires-Dist: sphinx-gallery; extra == 'docs'
Requires-Dist: sphinxawesome-theme; extra == 'docs'
Requires-Dist: sphinxcontrib-programoutput; extra == 'docs'
